OmicsAnalysis/ClinicalDataSet.py
OmicsAnalysis/ContinuousOmicsDataSet.py
OmicsAnalysis/DLembedder.py
OmicsAnalysis/DataGenerator.py
OmicsAnalysis/DiscreteOmicsDataSet.py
OmicsAnalysis/Embeddings.py
OmicsAnalysis/InteractionNetwork.py
OmicsAnalysis/OmicsDataSet.py
OmicsAnalysis/PropagationModel.py
OmicsAnalysis/PyLouvain.py
OmicsAnalysis/__init__.py
OmicsAnalysis/rcc.py
OmicsAnalysis-0.14.2.dist-info/METADATA
OmicsAnalysis-0.14.2.dist-info/WHEEL
OmicsAnalysis-0.14.2.dist-info/top_level.txt
OmicsAnalysis-0.14.2.dist-info/RECORD
