Metadata-Version: 2.1
Name: OmicsAnalysis
Version: 0.14.2
Summary: General omics data analysis tools
Home-page: https://github.ugent.be/mlarmuse/OmicsAnalysis
Author: Maarten Larmuseau
Author-email: maarten.larmuseau@ugent.be
License: MIT
Platform: UNKNOWN
Classifier: Development Status :: 3 - Alpha
Requires-Dist: numpy (>=1.9.1)
Requires-Dist: pandas (>=0.24)
Requires-Dist: scipy (>=1.2)
Requires-Dist: tensorflow (>=1.10)
Requires-Dist: scikit-learn (>0.19)
Requires-Dist: keras (>=2.2)
Requires-Dist: matplotlib (>=3.0)
Requires-Dist: lifelines
Requires-Dist: networkx
Requires-Dist: umap
Requires-Dist: statsmodels
